google_pay_token_decryption/__init__.py
google_pay_token_decryption/google_pay.py
google_pay_token_decryption-0.1.0.dist-info/WHEEL
google_pay_token_decryption-0.1.0.dist-info/METADATA
google_pay_token_decryption-0.1.0.dist-info/RECORD
