Metadata-Version: 2.1
Name: google-pay-token-decryption
Version: 0.1.0
Summary: Python package to verify and decrypt Google Pay tokens
Home-page: https://github.com/yoyowallet/google-pay-token-decryption
License: MIT
Keywords: google pay
Author: Yoyo Wallet
Author-email: dev@yoyowallet.com
Maintainer: Yoyo Wallet
Maintainer-email: dev@yoyowallet.com
Requires-Python: >=3.8,<4.0
Classifier: Development Status :: 3 - Alpha
Classifier: Intended Audience :: Developers
Classifier: License :: OSI Approved :: MIT License
Classifier: Natural Language :: English
Classifier: Programming Language :: Python :: 3
Classifier: Programming Language :: Python :: 3.8
Classifier: Programming Language :: Python :: 3.9
Requires-Dist: cryptography (>=3.4.7,<4.0.0)
Project-URL: Repository, https://github.com/yoyowallet/google-pay-token-decryption
